uploadabletest.py
uploadabletest-0.1.dist-info/WHEEL
uploadabletest-0.1.dist-info/METADATA
uploadabletest-0.1.dist-info/RECORD
