Metadata-Version: 2.1
Name: uploadabletest
Version: 0.1
Summary: Test uploading
Home-page: https://example.com/
License: UNKNOWN
Author: Thomas Kluyver
Author-email: thomas@kluyver.me.uk
